file_retention/__init__.py
file_retention/__main__.py
file_retention/__version__.py
file_retention/file_retention.py
file_retention/functions.py
file_retention-0.3.2.dist-info/LICENSE
file_retention-0.3.2.dist-info/WHEEL
file_retention-0.3.2.dist-info/METADATA
file_retention-0.3.2.dist-info/RECORD
