Metadata-Version: 2.1
Name: file-retention
Version: 0.3.2
Summary: Delete files based on predefined dates
Home-page: https://github.com/ollemg/file_retention
Author: Gabriel de Mello Barbosa
Requires-Python: >=3.7,<4.0
Classifier: Programming Language :: Python :: 3
Classifier: Programming Language :: Python :: 3.7
Classifier: Programming Language :: Python :: 3.8
Classifier: Programming Language :: Python :: 3.9
Requires-Dist: PyYAML (>=6.0,<7.0)
Requires-Dist: click (>=8.0.3,<9.0.0)
Project-URL: Repository, https://github.com/ollemg/file_retention
